[
    {
        "id":1,
        "name":"Baby Infant",
        "price":7999,
        "category":"A",
        "image":"https://bachaaparty.com/cdn/shop/products/Z41879_540x.jpg?v=1672835991"
    },
    {
        "id":2,
        "name":"Baby Infant",
        "price":5999,
        "category":"A",
        "image":"https://bachaaparty.com/cdn/shop/files/IMG_3125_3c751e54-6d7f-43b6-be15-849a56ddaa02_540x.jpg?v=1685598847"
    },
    {
        "id":3,
        "name":"Baby Infant",
        "price":4999,
        "category":"A",
        "image":"https://bachaaparty.com/cdn/shop/products/z68204_540x.jpg?v=1671863827"
    },
    {
        "id":4,
        "name":"Baby Infant",
        "price":3999,
        "category":"A",
        "image":"https://bachaaparty.com/cdn/shop/files/BPE_2820_d5ba40d8-a537-4de7-9a9b-28b778a0c3c9_540x.jpg?v=1716372719"
    },
    {
        "id":5,
        "name":"Baby Infant",
        "price":7999,
        "category":"A",
        "image":"https://bachaaparty.com/cdn/shop/products/Z41879_540x.jpg?v=1672835991"
    },
    {
        "id":6,
        "name":"Baby Infant",
        "price":5999,
        "category":"A",
        "image":"https://bachaaparty.com/cdn/shop/files/IMG_3125_3c751e54-6d7f-43b6-be15-849a56ddaa02_540x.jpg?v=1685598847"
    },
    {
        "id":7,
        "name":"Baby Infant",
        "price":4999,
        "category":"A",
        "image":"https://bachaaparty.com/cdn/shop/products/z68204_540x.jpg?v=1671863827"
    },
    {
        "id":8,
        "name":"Baby Infant",
        "price":3999,
        "category":"A",
        "image":"https://bachaaparty.com/cdn/shop/files/BPE_2820_d5ba40d8-a537-4de7-9a9b-28b778a0c3c9_540x.jpg?v=1716372719"
    },
    {
        "id":9,
        "name":"Bags Books",
        "price":1000,
        "category":"B",
        "image":"https://bachaaparty.com/cdn/shop/files/DSC09122_0211010e-b526-4f43-bf97-fb7de635276c_540x.jpg?v=1691384426"
    },
    {
        "id":10,
        "name":"Bags Books",
        "price":1000,
        "category":"B",
        "image":"https://bachaaparty.com/cdn/shop/files/DSC_2836_540x.jpg?v=1710748937"
    },
    {
        "id":11,
        "name":"Bags Books",
        "price":1000,
        "category":"B",
        "image":"https://bachaaparty.com/cdn/shop/files/PS115749_540x.jpg?v=1708673809"
    },
    {
        "id":12,
        "name":"Bags Books",
        "price":1000,
        "category":"B",
        "image":"https://bachaaparty.com/cdn/shop/files/BPE_0923_76b0f620-39b6-4123-8b09-d4462efe6f80_540x.jpg?v=1721481979"
    },
    {
        "id":13,
        "name":"Bags Books",
        "price":1000,
        "category":"B",
        "image":"https://bachaaparty.com/cdn/shop/files/DSC09122_0211010e-b526-4f43-bf97-fb7de635276c_540x.jpg?v=1691384426"
    },
    {
        "id":14,
        "name":"Bags Books",
        "price":1000,
        "category":"B",
        "image":"https://bachaaparty.com/cdn/shop/files/DSC_2836_540x.jpg?v=1710748937"
    },
    {
        "id":15,
        "name":"Bags Books",
        "price":1000,
        "category":"B",
        "image":"https://bachaaparty.com/cdn/shop/files/PS115749_540x.jpg?v=1708673809"
    },
    {
        "id":16,
        "name":"Bags Books",
        "price":1000,
        "category":"B",
        "image":"https://bachaaparty.com/cdn/shop/files/BPE_0923_76b0f620-39b6-4123-8b09-d4462efe6f80_540x.jpg?v=1721481979"
    },
    {
        "id":17,
        "name":"Kids Cloth",
        "price":1000,
        "category":"C",
        "image":"https://bachaaparty.com/cdn/shop/collections/Infant_Girls_ac0872b8-2e27-4308-ad55-444c6343a7dc_360x.jpg?v=1722436962"
    },
    {
        "id":18,
        "name":"Kids Cloth",
        "price":1000,
        "category":"C",
        "image":"https://bachaaparty.com/cdn/shop/collections/Infant_Girls_ac0872b8-2e27-4308-ad55-444c6343a7dc_360x.jpg?v=1722436962"
    },
    {
        "id":19,
        "name":"Kids Cloth",
        "price":1000,
        "category":"C",
        "image":"https://bachaaparty.com/cdn/shop/collections/Infant_Girls_ac0872b8-2e27-4308-ad55-444c6343a7dc_360x.jpg?v=1722436962"
    },
    {
        "id":20,
        "name":"Kids Cloth",
        "price":1000,
        "category":"C",
        "image":"https://bachaaparty.com/cdn/shop/collections/Infant_Girls_ac0872b8-2e27-4308-ad55-444c6343a7dc_360x.jpg?v=1722436962"
    },
    {
        "id":21,
        "name":"Kids Cloth",
        "price":1000,
        "category":"C",
        "image":"https://bachaaparty.com/cdn/shop/collections/Infant_Girls_ac0872b8-2e27-4308-ad55-444c6343a7dc_360x.jpg?v=1722436962"
    },
    {
        "id":22,
        "name":"Kids Cloth",
        "price":1000,
        "category":"C",
        "image":"https://bachaaparty.com/cdn/shop/collections/Infant_Girls_ac0872b8-2e27-4308-ad55-444c6343a7dc_360x.jpg?v=1722436962"
    },
    {
        "id":23,
        "name":"Kids Cloth",
        "price":1000,
        "category":"C",
        "image":"https://bachaaparty.com/cdn/shop/collections/Infant_Girls_ac0872b8-2e27-4308-ad55-444c6343a7dc_360x.jpg?v=1722436962"
    },
    {
        "id":24,
        "name":"Kids Cloth",
        "price":1000,
        "category":"C",
        "image":"https://bachaaparty.com/cdn/shop/collections/Infant_Girls_ac0872b8-2e27-4308-ad55-444c6343a7dc_360x.jpg?v=1722436962"
    },
    {
        "id":25,
        "name":"Kids Shirt",
        "price":800,
        "category":"D",
        "image":"https://bachaaparty.com/cdn/shop/collections/boys_apparel_b6fbb55b-21ad-486d-bcfc-0b8fb637adf5_360x.jpg?v=1722407527"
    },
    {
        "id":26,
        "name":"Kids Shirt",
        "price":800,
        "category":"D",
        "image":"https://bachaaparty.com/cdn/shop/collections/boys_apparel_b6fbb55b-21ad-486d-bcfc-0b8fb637adf5_360x.jpg?v=1722407527"
    },
    {
        "id":27,
        "name":"Kids Shirt",
        "price":800,
        "category":"D",
        "image":"https://bachaaparty.com/cdn/shop/collections/boys_apparel_b6fbb55b-21ad-486d-bcfc-0b8fb637adf5_360x.jpg?v=1722407527"
    },
    {
        "id":28,
        "name":"Kids Shirt",
        "price":800,
        "category":"D",
        "image":"https://bachaaparty.com/cdn/shop/collections/boys_apparel_b6fbb55b-21ad-486d-bcfc-0b8fb637adf5_360x.jpg?v=1722407527"
    },
    {
        "id":29,
        "name":"Kids Shirt",
        "price":800,
        "category":"D",
        "image":"https://bachaaparty.com/cdn/shop/collections/boys_apparel_b6fbb55b-21ad-486d-bcfc-0b8fb637adf5_360x.jpg?v=1722407527"
    },
    {
        "id":30,
        "name":"Kids Shirt",
        "price":800,
        "category":"D",
        "image":"https://bachaaparty.com/cdn/shop/collections/boys_apparel_b6fbb55b-21ad-486d-bcfc-0b8fb637adf5_360x.jpg?v=1722407527"
    },
    {
        "id":31,
        "name":"Kids Shirt",
        "price":800,
        "category":"D",
        "image":"https://bachaaparty.com/cdn/shop/collections/boys_apparel_b6fbb55b-21ad-486d-bcfc-0b8fb637adf5_360x.jpg?v=1722407527"
    },
    {
        "id":32,
        "name":"Kids Shirt",
        "price":800,
        "category":"D",
        "image":"https://bachaaparty.com/cdn/shop/collections/boys_apparel_b6fbb55b-21ad-486d-bcfc-0b8fb637adf5_360x.jpg?v=1722407527"
    },
    {
        "id":33,
        "name":"Boys & Girls Short",
        "price":1000,
        "category":"E",
        "image":"https://bachaaparty.com/cdn/shop/collections/teens_360x.jpg?v=1722428543"
    },
    {
        "id":34,
        "name":"Boys & Girls Short",
        "price":1000,
        "category":"E",
        "image":"https://bachaaparty.com/cdn/shop/collections/teens_360x.jpg?v=1722428543"
    },
    {
        "id":35,
        "name":"Boys & Girls Short",
        "price":1000,
        "category":"E",
        "image":"https://bachaaparty.com/cdn/shop/collections/teens_360x.jpg?v=1722428543"
    },
    {
        "id":36,
        "name":"Boys & Girls Short",
        "price":1000,
        "category":"E",
        "image":"https://bachaaparty.com/cdn/shop/collections/teens_360x.jpg?v=1722428543"
    },
    {
        "id":37,
        "name":"Boys & Girls Short",
        "price":1000,
        "category":"E",
        "image":"https://bachaaparty.com/cdn/shop/collections/teens_360x.jpg?v=1722428543"
    },
    {
        "id":38,
        "name":"Boys & Girls Short",
        "price":1000,
        "category":"E",
        "image":"https://bachaaparty.com/cdn/shop/collections/teens_360x.jpg?v=1722428543"
    },
    {
        "id":39,
        "name":"Boys & Girls Short",
        "price":1000,
        "category":"E",
        "image":"https://bachaaparty.com/cdn/shop/collections/teens_360x.jpg?v=1722428543"
    },
    {
        "id":40,
        "name":"Boys & Girls Short",
        "price":1000,
        "category":"E",
        "image":"https://bachaaparty.com/cdn/shop/collections/teens_360x.jpg?v=1722428543"
    },
    {
        "id":6,
        "name":"Baby Gifts",
        "price":799,
        "category":"F",
        "image":"https://bachaaparty.com/cdn/shop/collections/kids_friday_tiletoys_360x.jpg?v=1722408310"
    },
    {
        "id":6,
        "name":"Baby Gifts",
        "price":799,
        "category":"F",
        "image":"https://bachaaparty.com/cdn/shop/collections/kids_friday_tiletoys_360x.jpg?v=1722408310"
    },
    {
        "id":6,
        "name":"Baby Gifts",
        "price":799,
        "category":"F",
        "image":"https://bachaaparty.com/cdn/shop/collections/kids_friday_tiletoys_360x.jpg?v=1722408310"
    },
    {
        "id":6,
        "name":"Baby Gifts",
        "price":799,
        "category":"F",
        "image":"https://bachaaparty.com/cdn/shop/collections/kids_friday_tiletoys_360x.jpg?v=1722408310"
    },
    {
        "id":7,
        "name":"Girls Jewelery",
        "price":800,
        "category":"G",
        "image":"https://bachaaparty.com/cdn/shop/collections/kids_friday_tileinfant_accessories_360x.jpg?v=1722408221"
    },
    {
        "id":7,
        "name":"Girls Jewelery",
        "price":800,
        "category":"G",
        "image":"https://bachaaparty.com/cdn/shop/collections/kids_friday_tileinfant_accessories_360x.jpg?v=1722408221"
    },
    {
        "id":7,
        "name":"Girls Jewelery",
        "price":800,
        "category":"G",
        "image":"https://bachaaparty.com/cdn/shop/collections/kids_friday_tileinfant_accessories_360x.jpg?v=1722408221"
    },
    {
        "id":7,
        "name":"Girls Jewelery",
        "price":800,
        "category":"G",
        "image":"https://bachaaparty.com/cdn/shop/collections/kids_friday_tileinfant_accessories_360x.jpg?v=1722408221"
    },
    {
        "id":8,
        "name":"baby Girls Shirt",
        "price":800,
        "category":"H",
        "image":"https://bachaaparty.com/cdn/shop/collections/girls_apparel_9de08cbf-0750-4c1e-9656-96cd77df4d7b_360x.jpg?v=1722407589"
    },
    {
        "id":8,
        "name":"baby Girls Shirt",
        "price":800,
        "category":"H",
        "image":"https://bachaaparty.com/cdn/shop/collections/girls_apparel_9de08cbf-0750-4c1e-9656-96cd77df4d7b_360x.jpg?v=1722407589"
    },
    {
        "id":8,
        "name":"baby Girls Shirt",
        "price":800,
        "category":"H",
        "image":"https://bachaaparty.com/cdn/shop/collections/girls_apparel_9de08cbf-0750-4c1e-9656-96cd77df4d7b_360x.jpg?v=1722407589"
    },
    {
        "id":8,
        "name":"baby Girls Shirt",
        "price":800,
        "category":"H",
        "image":"https://bachaaparty.com/cdn/shop/collections/girls_apparel_9de08cbf-0750-4c1e-9656-96cd77df4d7b_360x.jpg?v=1722407589"
    },
    {
        "id":9,
        "name":"Girls Shoes",
        "price":1299,
        "category":"I",
        "image":"https://bachaaparty.com/cdn/shop/collections/girls_shoes_360x.jpg?v=1722407783"
    },
    {
        "id":9,
        "name":"Girls Shoes",
        "price":1299,
        "category":"I",
        "image":"https://bachaaparty.com/cdn/shop/collections/girls_shoes_360x.jpg?v=1722407783"
    },
    {
        "id":9,
        "name":"Girls Shoes",
        "price":1299,
        "category":"I",
        "image":"https://bachaaparty.com/cdn/shop/collections/girls_shoes_360x.jpg?v=1722407783"
    },
    {
        "id":9,
        "name":"Girls Shoes",
        "price":1299,
        "category":"I",
        "image":"https://bachaaparty.com/cdn/shop/collections/girls_shoes_360x.jpg?v=1722407783"
    },
    {
        "id":10,
        "name":"Baby Shoes",
        "price":799,
        "category":"J",
        "image":"https://bachaaparty.com/cdn/shop/collections/z627092027_1_540x_6f014bcb-d679-437c-97e7-0f3d72c9fcca_360x.webp?v=1722407482"
    },
    {
        "id":10,
        "name":"Baby Shoes",
        "price":799,
        "category":"J",
        "image":"https://bachaaparty.com/cdn/shop/collections/z627092027_1_540x_6f014bcb-d679-437c-97e7-0f3d72c9fcca_360x.webp?v=1722407482"
    },
    {
        "id":10,
        "name":"Baby Shoes",
        "price":799,
        "category":"J",
        "image":"https://bachaaparty.com/cdn/shop/collections/z627092027_1_540x_6f014bcb-d679-437c-97e7-0f3d72c9fcca_360x.webp?v=1722407482"
    },
    {
        "id":10,
        "name":"Baby Shoes",
        "price":799,
        "category":"J",
        "image":"https://bachaaparty.com/cdn/shop/collections/z627092027_1_540x_6f014bcb-d679-437c-97e7-0f3d72c9fcca_360x.webp?v=1722407482"
    },
    {
        "id":11,
        "name":"Boys Shoes ",
        "price":2000,
        "category":"K",
        "image":"https://bachaaparty.com/cdn/shop/collections/Boy_shoes_74db8cff-56ed-4510-a9c5-c0266e23635f_360x.jpg?v=1722407566"
    },
    {
        "id":11,
        "name":"Boys Shoes ",
        "price":2000,
        "category":"K",
        "image":"https://bachaaparty.com/cdn/shop/collections/Boy_shoes_74db8cff-56ed-4510-a9c5-c0266e23635f_360x.jpg?v=1722407566"
    },
    {
        "id":11,
        "name":"Boys Shoes ",
        "price":2000,
        "category":"K",
        "image":"https://bachaaparty.com/cdn/shop/collections/Boy_shoes_74db8cff-56ed-4510-a9c5-c0266e23635f_360x.jpg?v=1722407566"
    },
    {
        "id":11,
        "name":"Boys Shoes ",
        "price":2000,
        "category":"K",
        "image":"https://bachaaparty.com/cdn/shop/collections/Boy_shoes_74db8cff-56ed-4510-a9c5-c0266e23635f_360x.jpg?v=1722407566"
    },
    {
        "id":12,
        "name":"Giral Apperal",
        "price":799,
        "category":"L",
        "image":"https://bachaaparty.com/cdn/shop/collections/girls_apparel_9de08cbf-0750-4c1e-9656-96cd77df4d7b_360x.jpg?v=1722407589"
    },
    {
        "id":12,
        "name":"Giral Apperal",
        "price":799,
        "category":"L",
        "image":"https://bachaaparty.com/cdn/shop/collections/girls_apparel_9de08cbf-0750-4c1e-9656-96cd77df4d7b_360x.jpg?v=1722407589"
    },
    {
        "id":12,
        "name":"Giral Apperal",
        "price":799,
        "category":"L",
        "image":"https://bachaaparty.com/cdn/shop/collections/girls_apparel_9de08cbf-0750-4c1e-9656-96cd77df4d7b_360x.jpg?v=1722407589"
    },
    {
        "id":12,
        "name":"Giral Apperal",
        "price":799,
        "category":"L",
        "image":"https://bachaaparty.com/cdn/shop/collections/girls_apparel_9de08cbf-0750-4c1e-9656-96cd77df4d7b_360x.jpg?v=1722407589"
    }
]